{
  "user": "Aimee",
  "deployment_id": "permA",
  "long_term_preferences_days_1_15": {
    "microwave_time": "medium",
    "occlusion_relevance": "relevant",
    "robot_speed": "medium",
    "skewering_axis": "perpendicular",
    "transfer_mode": "outside mouth",
    "outside_mouth_distance": "7cm",
    "robot_ready_cue": "speech",
    "bite_initiation_feeding": "open mouth",
    "bite_initiation_drinking": "open mouth",
    "bite_initiation_wiping": "open mouth",
    "robot_bite_available_cue": "speech",
    "bite_completion_feeding": "perception",
    "bite_completion_drinking": "perception",
    "bite_completion_wiping": "perception",
    "web_interface_confirmation": "yes",
    "retract_between_bites": "no",
    "bite_ordering_preference": "N/A",
    "bite_dipping_preference": "N/A",
    "amount_to_dip": "more",
    "wait_before_autocontinue_seconds": "10"
  },
  "daily_entries": [
    {
      "day": 1,
      "context": {
        "meal": "cantaloupes, bananas, watermelon",
        "setting": "Watching TV",
        "affective_state": "Energetic"
      },
      "preferences": {
        "microwave_time": "no microwave",
        "occlusion_relevance": "minimize front occlusion",
        "robot_speed": "fast",
        "skewering_axis": "perpendicular to major axis",
        "transfer_mode": "outside mouth transfer",
        "outside_mouth_distance": "medium",
        "robot_ready_cue": "no cue",
        "bite_initiation_feeding": "open mouth",
        "bite_initiation_drinking": "open mouth",
        "bite_initiation_wiping": "open mouth",
        "robot_bite_available_cue": "no cue",
        "bite_completion_feeding": "perception",
        "bite_completion_drinking": "perception",
        "bite_completion_wiping": "perception",
        "web_interface_confirmation": "no",
        "retract_between_bites": "no",
        "bite_ordering_preference": "alternate X and Y",
        "bite_dipping_preference": "do not dip",
        "amount_to_dip": "less",
        "wait_before_autocontinue_seconds": "100"
      }
    },
    {
      "day": 2,
      "context": {
        "meal": "buffalo chicken bites, potato wedges, and ranch dressing",
        "setting": "Watching TV",
        "affective_state": "Exploratory"
      },
      "preferences": {
        "microwave_time": "2 min",
        "occlusion_relevance": "minimize front occlusion",
        "robot_speed": "slow",
        "skewering_axis": "perpendicular to major axis",
        "transfer_mode": "outside mouth transfer",
        "outside_mouth_distance": "medium",
        "robot_ready_cue": "LED",
        "bite_initiation_feeding": "open mouth",
        "bite_initiation_drinking": "open mouth",
        "bite_initiation_wiping": "open mouth",
        "robot_bite_available_cue": "no cue",
        "bite_completion_feeding": "perception",
        "bite_completion_drinking": "perception",
        "bite_completion_wiping": "perception",
        "web_interface_confirmation": "no",
        "retract_between_bites": "no",
        "bite_ordering_preference": "alternate X and Y",
        "bite_dipping_preference": "dip both X and Y in Z",
        "amount_to_dip": "more",
        "wait_before_autocontinue_seconds": "100"
      }
    },
    {
      "day": 3,
      "context": {
        "meal": "buffalo chicken bites, potato wedges, and ranch dressing",
        "setting": "Social",
        "affective_state": "Fatigued"
      },
      "preferences": {
        "microwave_time": "2 min",
        "occlusion_relevance": "minimize left occlusion",
        "robot_speed": "slow",
        "skewering_axis": "perpendicular to major axis",
        "transfer_mode": "inside mouth transfer",
        "outside_mouth_distance": "near",
        "robot_ready_cue": "LED",
        "bite_initiation_feeding": "autocontinue",
        "bite_initiation_drinking": "autocontinue",
        "bite_initiation_wiping": "autocontinue",
        "robot_bite_available_cue": "LED",
        "bite_completion_feeding": "autocontinue",
        "bite_completion_drinking": "autocontinue",
        "bite_completion_wiping": "autocontinue",
        "web_interface_confirmation": "no",
        "retract_between_bites": "no",
        "bite_ordering_preference": "alternate X and Y",
        "bite_dipping_preference": "dip both X and Y in Z",
        "amount_to_dip": "more",
        "wait_before_autocontinue_seconds": "1000"
      }
    },
    {
      "day": 4,
      "context": {
        "meal": "chicken nuggets, broccoli, and ketchup",
        "setting": "Personal",
        "affective_state": "Slower"
      },
      "preferences": {
        "microwave_time": "2 min",
        "occlusion_relevance": "do not consider occlusion",
        "robot_speed": "slow",
        "skewering_axis": "perpendicular to major axis",
        "transfer_mode": "outside mouth transfer",
        "outside_mouth_distance": "medium",
        "robot_ready_cue": "speech",
        "bite_initiation_feeding": "open mouth",
        "bite_initiation_drinking": "open mouth",
        "bite_initiation_wiping": "open mouth",
        "robot_bite_available_cue": "speech",
        "bite_completion_feeding": "perception",
        "bite_completion_drinking": "perception",
        "bite_completion_wiping": "perception",
        "web_interface_confirmation": "yes",
        "retract_between_bites": "no",
        "bite_ordering_preference": "alternate X and Y",
        "bite_dipping_preference": "dip X in Z",
        "amount_to_dip": "more",
        "wait_before_autocontinue_seconds": "100"
      }
    },
    {
      "day": 5,
      "context": {
        "meal": "strawberries with whipped cream",
        "setting": "Personal",
        "affective_state": "Neutral"
      },
      "preferences": {
        "microwave_time": "no microwave",
        "occlusion_relevance": "do not consider occlusion",
        "robot_speed": "medium",
        "skewering_axis": "perpendicular to major axis",
        "transfer_mode": "outside mouth transfer",
        "outside_mouth_distance": "medium",
        "robot_ready_cue": "speech",
        "bite_initiation_feeding": "open mouth",
        "bite_initiation_drinking": "open mouth",
        "bite_initiation_wiping": "open mouth",
        "robot_bite_available_cue": "speech",
        "bite_completion_feeding": "perception",
        "bite_completion_drinking": "perception",
        "bite_completion_wiping": "perception",
        "web_interface_confirmation": "yes",
        "retract_between_bites": "no",
        "bite_ordering_preference": "alternate X and Y",
        "bite_dipping_preference": "dip X in Z",
        "amount_to_dip": "more",
        "wait_before_autocontinue_seconds": "10"
      }
    },
    {
      "day": 6,
      "context": {
        "meal": "general tso’s chicken and broccoli",
        "setting": "Social + Watching TV",
        "affective_state": "Slower"
      },
      "preferences": {
        "microwave_time": "3 min",
        "occlusion_relevance": "minimize front occlusion",
        "robot_speed": "slow",
        "skewering_axis": "perpendicular to major axis",
        "transfer_mode": "outside mouth transfer",
        "outside_mouth_distance": "medium",
        "robot_ready_cue": "no cue",
        "bite_initiation_feeding": "button",
        "bite_initiation_drinking": "button",
        "bite_initiation_wiping": "button",
        "robot_bite_available_cue": "no cue",
        "bite_completion_feeding": "button",
        "bite_completion_drinking": "button",
        "bite_completion_wiping": "button",
        "web_interface_confirmation": "no",
        "retract_between_bites": "yes",
        "bite_ordering_preference": "alternate X and Y",
        "bite_dipping_preference": "do not dip",
        "amount_to_dip": "more",
        "wait_before_autocontinue_seconds": "1000"
      }
    },
    {
      "day": 7,
      "context": {
        "meal": "chicken breast strips and hash brown",
        "setting": "Watching TV",
        "affective_state": "Neutral"
      },
      "preferences": {
        "microwave_time": "3 min",
        "occlusion_relevance": "minimize front occlusion",
        "robot_speed": "medium",
        "skewering_axis": "perpendicular to major axis",
        "transfer_mode": "outside mouth transfer",
        "outside_mouth_distance": "medium",
        "robot_ready_cue": "no cue",
        "bite_initiation_feeding": "open mouth",
        "bite_initiation_drinking": "open mouth",
        "bite_initiation_wiping": "open mouth",
        "robot_bite_available_cue": "no cue",
        "bite_completion_feeding": "perception",
        "bite_completion_drinking": "perception",
        "bite_completion_wiping": "perception",
        "web_interface_confirmation": "no",
        "retract_between_bites": "no",
        "bite_ordering_preference": "alternate X and Y",
        "bite_dipping_preference": "do not dip",
        "amount_to_dip": "more",
        "wait_before_autocontinue_seconds": "100"
      }
    },
    {
      "day": 8,
      "context": {
        "meal": "cantaloupes, bananas, watermelon",
        "setting": "Watching TV",
        "affective_state": "Neutral"
      },
      "preferences": {
        "microwave_time": "no microwave",
        "occlusion_relevance": "minimize front occlusion",
        "robot_speed": "medium",
        "skewering_axis": "perpendicular to major axis",
        "transfer_mode": "outside mouth transfer",
        "outside_mouth_distance": "medium",
        "robot_ready_cue": "no cue",
        "bite_initiation_feeding": "open mouth",
        "bite_initiation_drinking": "open mouth",
        "bite_initiation_wiping": "open mouth",
        "robot_bite_available_cue": "no cue",
        "bite_completion_feeding": "perception",
        "bite_completion_drinking": "perception",
        "bite_completion_wiping": "perception",
        "web_interface_confirmation": "no",
        "retract_between_bites": "no",
        "bite_ordering_preference": "alternate X and Y",
        "bite_dipping_preference": "do not dip",
        "amount_to_dip": "more",
        "wait_before_autocontinue_seconds": "100"
      }
    },
    {
      "day": 9,
      "context": {
        "meal": "chicken nuggets, broccoli, and ketchup",
        "setting": "Social",
        "affective_state": "Fatigued"
      },
      "preferences": {
        "microwave_time": "2 min",
        "occlusion_relevance": "minimize left occlusion",
        "robot_speed": "slow",
        "skewering_axis": "perpendicular to major axis",
        "transfer_mode": "inside mouth transfer",
        "outside_mouth_distance": "near",
        "robot_ready_cue": "no cue",
        "bite_initiation_feeding": "button",
        "bite_initiation_drinking": "button",
        "bite_initiation_wiping": "button",
        "robot_bite_available_cue": "LED",
        "bite_completion_feeding": "button",
        "bite_completion_drinking": "autocontinue",
        "bite_completion_wiping": "autocontinue",
        "web_interface_confirmation": "no",
        "retract_between_bites": "yes",
        "bite_ordering_preference": "alternate X and Y",
        "bite_dipping_preference": "dip X in Z",
        "amount_to_dip": "more",
        "wait_before_autocontinue_seconds": "1000"
      }
    },
    {
      "day": 10,
      "context": {
        "meal": "chicken breast strips and hash brown",
        "setting": "Social",
        "affective_state": "Exploratory"
      },
      "preferences": {
        "microwave_time": "3 min",
        "occlusion_relevance": "minimize left occlusion",
        "robot_speed": "medium",
        "skewering_axis": "perpendicular to major axis",
        "transfer_mode": "outside mouth transfer",
        "outside_mouth_distance": "medium",
        "robot_ready_cue": "LED",
        "bite_initiation_feeding": "button",
        "bite_initiation_drinking": "button",
        "bite_initiation_wiping": "button",
        "robot_bite_available_cue": "LED",
        "bite_completion_feeding": "button",
        "bite_completion_drinking": "button",
        "bite_completion_wiping": "button",
        "web_interface_confirmation": "yes",
        "retract_between_bites": "yes",
        "bite_ordering_preference": "alternate X and Y",
        "bite_dipping_preference": "do not dip",
        "amount_to_dip": "more",
        "wait_before_autocontinue_seconds": "1000"
      }
    },
    {
      "day": 11,
      "context": {
        "meal": "bite-sized sandwiches",
        "setting": "Watching TV",
        "affective_state": "Exploratory"
      },
      "preferences": {
        "microwave_time": "3 min",
        "occlusion_relevance": "minimize front occlusion",
        "robot_speed": "fast",
        "skewering_axis": "perpendicular to major axis",
        "transfer_mode": "outside mouth transfer",
        "outside_mouth_distance": "medium",
        "robot_ready_cue": "LED",
        "bite_initiation_feeding": "open mouth",
        "bite_initiation_drinking": "open mouth",
        "bite_initiation_wiping": "open mouth",
        "robot_bite_available_cue": "LED",
        "bite_completion_feeding": "perception",
        "bite_completion_drinking": "perception",
        "bite_completion_wiping": "perception",
        "web_interface_confirmation": "no",
        "retract_between_bites": "no",
        "bite_ordering_preference": "alternate X and Y",
        "bite_dipping_preference": "do not dip",
        "amount_to_dip": "more",
        "wait_before_autocontinue_seconds": "100"
      }
    },
    {
      "day": 12,
      "context": {
        "meal": "chicken nuggets, broccoli, and ketchup",
        "setting": "Social",
        "affective_state": "Slower"
      },
      "preferences": {
        "microwave_time": "3 min",
        "occlusion_relevance": "minimize left occlusion",
        "robot_speed": "slow",
        "skewering_axis": "perpendicular to major axis",
        "transfer_mode": "outside mouth transfer",
        "outside_mouth_distance": "medium",
        "robot_ready_cue": "no cue",
        "bite_initiation_feeding": "button",
        "bite_initiation_drinking": "button",
        "bite_initiation_wiping": "button",
        "robot_bite_available_cue": "no cue",
        "bite_completion_feeding": "button",
        "bite_completion_drinking": "button",
        "bite_completion_wiping": "button",
        "web_interface_confirmation": "no",
        "retract_between_bites": "yes",
        "bite_ordering_preference": "alternate X and Y",
        "bite_dipping_preference": "dip X in Z",
        "amount_to_dip": "more",
        "wait_before_autocontinue_seconds": "1000"
      }
    },
    {
      "day": 13,
      "context": {
        "meal": "bite-sized sandwiches",
        "setting": "Personal",
        "affective_state": "Fatigued"
      },
      "preferences": {
        "microwave_time": "3 min",
        "occlusion_relevance": "do not consider occlusion",
        "robot_speed": "slow",
        "skewering_axis": "perpendicular to major axis",
        "transfer_mode": "inside mouth transfer",
        "outside_mouth_distance": "near",
        "robot_ready_cue": "no cue",
        "bite_initiation_feeding": "autocontinue",
        "bite_initiation_drinking": "autocontinue",
        "bite_initiation_wiping": "autocontinue",
        "robot_bite_available_cue": "no cue",
        "bite_completion_feeding": "autocontinue",
        "bite_completion_drinking": "autocontinue",
        "bite_completion_wiping": "autocontinue",
        "web_interface_confirmation": "no",
        "retract_between_bites": "no",
        "bite_ordering_preference": "alternate X and Y",
        "bite_dipping_preference": "do not dip",
        "amount_to_dip": "more",
        "wait_before_autocontinue_seconds": "10"
      }
    },
    {
      "day": 14,
      "context": {
        "meal": "breaded fish bites, roasted potatoes, tartar sauce",
        "setting": "Watching TV",
        "affective_state": "Exploratory"
      },
      "preferences": {
        "microwave_time": "2 min",
        "occlusion_relevance": "minimize front occlusion",
        "robot_speed": "medium",
        "skewering_axis": "perpendicular to major axis",
        "transfer_mode": "outside mouth transfer",
        "outside_mouth_distance": "medium",
        "robot_ready_cue": "no cue",
        "bite_initiation_feeding": "button",
        "bite_initiation_drinking": "button",
        "bite_initiation_wiping": "button",
        "robot_bite_available_cue": "no cue",
        "bite_completion_feeding": "button",
        "bite_completion_drinking": "button",
        "bite_completion_wiping": "button",
        "web_interface_confirmation": "no",
        "retract_between_bites": "no",
        "bite_ordering_preference": "alternate X and Y",
        "bite_dipping_preference": "dip both X and Y in Z",
        "amount_to_dip": "more",
        "wait_before_autocontinue_seconds": "100"
      }
    },
    {
      "day": 15,
      "context": {
        "meal": "breaded fish bites, roasted potatoes, tartar sauce",
        "setting": "Working on laptop",
        "affective_state": "Fatigued"
      },
      "preferences": {
        "microwave_time": "2 min",
        "occlusion_relevance": "minimize front occlusion",
        "robot_speed": "slow",
        "skewering_axis": "perpendicular to major axis",
        "transfer_mode": "inside mouth transfer",
        "outside_mouth_distance": "near",
        "robot_ready_cue": "speech",
        "bite_initiation_feeding": "open mouth",
        "bite_initiation_drinking": "open mouth",
        "bite_initiation_wiping": "open mouth",
        "robot_bite_available_cue": "speech",
        "bite_completion_feeding": "perception",
        "bite_completion_drinking": "perception",
        "bite_completion_wiping": "perception",
        "web_interface_confirmation": "no",
        "retract_between_bites": "no",
        "bite_ordering_preference": "alternate X and Y",
        "bite_dipping_preference": "dip both X and Y in Z",
        "amount_to_dip": "more",
        "wait_before_autocontinue_seconds": "1000"
      }
    }
  ]
}